.mtn-ignore
LICENSE
README.txt
ez_setup.py
make-test-repo.sh
setup.py
setuptools_mtn.py
tests.py
setuptools_mtn.egg-info/PKG-INFO
setuptools_mtn.egg-info/SOURCES.txt
setuptools_mtn.egg-info/dependency_links.txt
setuptools_mtn.egg-info/entry_points.txt
setuptools_mtn.egg-info/top_level.txt