Metadata-Version: 1.0
Name: setuptools-mtn
Version: 0.4
Summary: setuptools support for discovering files kept in Monotone
Home-page: http://www.codefu.org/setuptools_mtn/
Author: Dale Sedivec
Author-email: dale@codefu.org
License: GPL
Keywords: setuptools monotone mtn
Platform: UNKNOWN
